{
  "objectInfo" : {
    "id" : "3Usk5NAG5VHkJwz62BjiGb",
    "name" : "Versioned Mapping - Delete",
    "type" : "DTEMPLATE",
    "metadata" : {
      "modelVersion" : {
        "major" : 0,
        "minor" : 0
      },
      "repoInfo" : {
        "repoHandle" : "01000E170000000000AU"
      },
      "contextAttributes" : [ {
        "name" : "id",
        "value" : "@1"
      } ],
      "additionalInfo" : {
        "description" : "",
        "contentType" : "JSON",
        "documentState" : "INVALID"
      }
    }
  },
  "dataFileExtension" : "zip",
  "updateTime" : "2023-07-21T14:39:41.444Z",
  "objectRefs" : [ ]
}